sniffs/__init__.py
sniffs/router.py
sniffs/sniffs.py
sniffs-0.6.3.dist-info/LICENSE
sniffs-0.6.3.dist-info/METADATA
sniffs-0.6.3.dist-info/WHEEL
sniffs-0.6.3.dist-info/RECORD
