Metadata-Version: 2.1
Name: sniffs
Version: 0.6.3
Summary: 
Author: surdouski
Author-email: michael.surdouski@gmail.com
Requires-Python: >=3.10,<4.0
Classifier: Programming Language :: Python :: 3
Classifier: Programming Language :: Python :: 3.10
Classifier: Programming Language :: Python :: 3.11
Classifier: Programming Language :: Python :: 3.12
Requires-Dist: paho-mqtt (==1.6.1)
Requires-Dist: pytest (>=8.1.1,<9.0.0)
